djforge_redis_multitokens/__init__.py
djforge_redis_multitokens/crypto.py
djforge_redis_multitokens/settings.py
djforge_redis_multitokens/tokens_auth.py
djforge_redis_multitokens/utils.py
djforge_redis_multitokens-0.0.3.dist-info/DESCRIPTION.rst
djforge_redis_multitokens-0.0.3.dist-info/METADATA
djforge_redis_multitokens-0.0.3.dist-info/RECORD
djforge_redis_multitokens-0.0.3.dist-info/WHEEL
djforge_redis_multitokens-0.0.3.dist-info/metadata.json
djforge_redis_multitokens-0.0.3.dist-info/top_level.txt
