Metadata-Version: 2.0
Name: djforge-redis-multitokens
Version: 0.0.3
Summary: Django REST Framework user auth using multiple tokens stored in Redis
Home-page: https://github.com/ToReforge/djforge-redis-multitokens
Author: ToReforge
Author-email: it@toreforge.com
License: MIT
Platform: UNKNOWN
Classifier: Development Status :: 4 - Beta
Classifier: Framework :: Django
Classifier: Intended Audience :: Developers
Classifier: License :: OSI Approved :: MIT License
Classifier: Operating System :: OS Independent
Classifier: Programming Language :: Python
Classifier: Programming Language :: Python :: 3
Requires-Dist: django
Requires-Dist: djangorestframework
Requires-Dist: passlib
